LICENSE
MANIFEST.in
README.md
setup.py
igamelister/__init__.py
igamelister/__main__.py
igamelister/text_helpers.py
igamelister.egg-info/PKG-INFO
igamelister.egg-info/SOURCES.txt
igamelister.egg-info/dependency_links.txt
igamelister.egg-info/entry_points.txt
igamelister.egg-info/requires.txt
igamelister.egg-info/top_level.txt
igamelister/amiga/__init__.py
igamelister/amiga/category.py
igamelister/amiga/chipset.py
igamelister/amiga/kickstart.py
igamelister/amiga/package.py
igamelister/amiga/person.py
igamelister/amiga/publisher.py
igamelister/amiga/region.py
igamelister/amiga/slave.py
igamelister/amiga/slave_flag.py
igamelister/amiga/info/__init__.py
igamelister/amiga/info/ada.py
igamelister/amiga/info/bitworld.py
igamelister/amiga/info/halloflight.py
igamelister/amiga/info/lemonamiga.py
igamelister/amiga/info/pouet.py
igamelister/amiga/info/source.py
igamelister/cli/__init__.py
igamelister/cli/config.py
igamelister/cli/dataset.py
igamelister/cli/igame.py
igamelister/cli/packages.py
igamelister/cli/slaves.py
igamelister/table/__init__.py
igamelister/table/align.py
igamelister/table/border.py
igamelister/table/column.py
igamelister/table/footer.py
igamelister/table/header.py
igamelister/table/section.py
igamelister/table/sectionitem.py
igamelister/table/table.py
igamelister/webscraper/__init__.py
igamelister/webscraper/interpolation.py
igamelister/webscraper/template.py
igamelister/webscraper/templates/ada.ini
igamelister/webscraper/templates/bitworld.ini
igamelister/webscraper/templates/halloflight.ini
igamelister/webscraper/templates/lemonamiga.ini
igamelister/webscraper/templates/pouet.ini
igamelister/webscraper/templates/whdload_apps.ini
igamelister/webscraper/templates/whdload_cracktros.ini
igamelister/webscraper/templates/whdload_demos.ini
igamelister/webscraper/templates/whdload_games.ini
igamelister/webscraper/templates/whdload_mags.ini
igamelister/webscraper/templates/whdload_news.ini
igamelister/webscraper/templates/whdload_package.ini