Metadata-Version: 2.1
Name: igamelister
Version: 0.8.4
Summary: A tool to generate nicely formatted gameslist and genre files for iGame, an AmigaOS WHDLoad launcher application.
Home-page: https://github.com/chris-vg/igamelister
Author: Chris Van Graas
Author-email: cvgcode@gmail.com
License: UNKNOWN
Platform: UNKNOWN
Classifier: Development Status :: 3 - Alpha
Classifier: Programming Language :: Python :: 3
Classifier: License :: OSI Approved :: MIT License
Classifier: Operating System :: OS Independent
